Metadata-Version: 2.1
Name: namebase
Version: 0.0.5
Summary: Python Client to interact with the Namebase API
Home-page: https://github.com/v1xingyue/namebase-py
Author: v1xingyue
Author-email: qixingyue@126.com
License: UNKNOWN
Keywords: namebase,handshake
Platform: UNKNOWN
Requires-Python: >=3.6
